{
  "source": "数据来源：50 组同题材对照样本",
  "sourceFile": "图表数据整理\\图表数据整理\\第二部分\\【二、图表4】女导演50部与男导演同题材对照_女主角年龄.csv",
  "buckets": [
    "<20",
    "20-29",
    "30-39",
    "40-49",
    "50+"
  ],
  "series": [
    {
      "group": "女导演作品",
      "total": 48,
      "buckets": [
        {
          "label": "<20",
          "count": 17,
          "pct": 35.4
        },
        {
          "label": "20-29",
          "count": 12,
          "pct": 25.0
        },
        {
          "label": "30-39",
          "count": 13,
          "pct": 27.1
        },
        {
          "label": "40-49",
          "count": 2,
          "pct": 4.2
        },
        {
          "label": "50+",
          "count": 4,
          "pct": 8.3
        }
      ]
    },
    {
      "group": "男导演对照",
      "total": 45,
      "buckets": [
        {
          "label": "<20",
          "count": 13,
          "pct": 28.9
        },
        {
          "label": "20-29",
          "count": 17,
          "pct": 37.8
        },
        {
          "label": "30-39",
          "count": 9,
          "pct": 20.0
        },
        {
          "label": "40-49",
          "count": 4,
          "pct": 8.9
        },
        {
          "label": "50+",
          "count": 2,
          "pct": 4.4
        }
      ]
    }
  ]
}
